QSimpleWidgets/QEditor.py
QSimpleWidgets/__init__.py
QSimpleWidgets-0.1.dist-info/METADATA
QSimpleWidgets-0.1.dist-info/WHEEL
QSimpleWidgets-0.1.dist-info/top_level.txt
QSimpleWidgets-0.1.dist-info/RECORD
