Metadata-Version: 2.1
Name: QSimpleWidgets
Version: 0.1
Summary: QtSimpleWidgets Adiciona Novos ao PyQt5
Home-page: https://github.com/eualexdev/QSimpleWidgets
Author: José Alexsandro || eualexdev
Author-email: eualex@github.com
License: UNKNOWN
Platform: UNKNOWN
Classifier: Programming Language :: Python :: 3
Classifier: License :: OSI Approved :: MIT License
Classifier: Operating System :: OS Independent
Requires-Python: >=3.6
